pytest_drivings/__init__.py
pytest_drivings/base_webdriver.py
pytest_drivings/exceptions.py
pytest_drivings/local_webdriver.py
pytest_drivings/settings.py
pytest_drivings/snapi.py
pytest_drivings/webdriver.py
pytest_drivings-1.0.4.dist-info/entry_points.txt
pytest_drivings-1.0.4.dist-info/WHEEL
pytest_drivings-1.0.4.dist-info/METADATA
pytest_drivings-1.0.4.dist-info/RECORD
